odoo/addons/stock_picking_batch_outgoing/README.rst
odoo/addons/stock_picking_batch_outgoing/__init__.py
odoo/addons/stock_picking_batch_outgoing/__manifest__.py
odoo/addons/stock_picking_batch_outgoing/i18n/es.po
odoo/addons/stock_picking_batch_outgoing/i18n/stock_picking_batch_outgoing.pot
odoo/addons/stock_picking_batch_outgoing/models/__init__.py
odoo/addons/stock_picking_batch_outgoing/models/stock_picking.py
odoo/addons/stock_picking_batch_outgoing/readme/CONTRIBUTORS.rst
odoo/addons/stock_picking_batch_outgoing/readme/DESCRIPTION.rst
odoo/addons/stock_picking_batch_outgoing/static/picking_outgoing_batch_list.png
odoo/addons/stock_picking_batch_outgoing/static/picking_pick_batch.png
odoo/addons/stock_picking_batch_outgoing/static/description/icon.png
odoo/addons/stock_picking_batch_outgoing/static/description/index.html
odoo/addons/stock_picking_batch_outgoing/tests/__init__.py
odoo/addons/stock_picking_batch_outgoing/tests/test_stock_picking_batch_outgoing.py
odoo/addons/stock_picking_batch_outgoing/views/stock_picking_views.xml
odoo_addon_stock_picking_batch_outgoing-15.0.1.2.0.dist-info/METADATA
odoo_addon_stock_picking_batch_outgoing-15.0.1.2.0.dist-info/WHEEL
odoo_addon_stock_picking_batch_outgoing-15.0.1.2.0.dist-info/top_level.txt
odoo_addon_stock_picking_batch_outgoing-15.0.1.2.0.dist-info/RECORD
