Metadata-Version: 2.1
Name: odoo-addon-stock_picking_batch_outgoing
Version: 15.0.1.2.0
Summary: Allows set on pickings the batch picking from last picking (out)
Home-page: https://github.com/OCA/stock-logistics-workflow
Author: Tecnativa, Odoo Community Association (OCA)
Author-email: support@odoo-community.org
License: AGPL-3
Classifier: Programming Language :: Python
Classifier: Framework :: Odoo
Classifier: Framework :: Odoo :: 15.0
Classifier: License :: OSI Approved :: GNU Affero General Public License v3
Classifier: Development Status :: 4 - Beta
Requires-Python: >=3.8
Requires-Dist: odoo-addon-stock-move-propagate-first-move <15.1dev,>=15.0dev
Requires-Dist: odoo <15.1dev,>=15.0a
